azmlclient/__init__.py
azmlclient/_version.py
azmlclient/base.py
azmlclient/base_databinding.py
azmlclient/base_databinding_blobs.py
azmlclient/clients.py
azmlclient/clients_callmodes.py
azmlclient/clients_config.py
azmlclient/py.typed
azmlclient/requests_utils.py
azmlclient/utils_requests.py
azmlclient/utils_testing.py
azmlclient-2.6.0.dist-info/LICENSE
azmlclient-2.6.0.dist-info/METADATA
azmlclient-2.6.0.dist-info/WHEEL
azmlclient-2.6.0.dist-info/top_level.txt
azmlclient-2.6.0.dist-info/RECORD
