Metadata-Version: 2.1
Name: azmlclient
Version: 2.6.0
Summary: A Python 3 client for AzureMl web services.
Home-page: https://github.com/smarie/python-azureml-client
Author: Sylvain MARIE <sylvain.marie@se.com>
Maintainer: Sylvain MARIE <sylvain.marie@se.com>
License: BSD 3-Clause
Download-URL: https://github.com/smarie/python-azureml-client/tarball/2.6.0
Keywords: Azure Machine Learning AzureML web services client network json
Platform: UNKNOWN
Classifier: Development Status :: 5 - Production/Stable
Classifier: Intended Audience :: Education
Classifier: Intended Audience :: Financial and Insurance Industry
Classifier: Intended Audience :: Science/Research
Classifier: Intended Audience :: Developers
Classifier: Intended Audience :: Information Technology
Classifier: License :: OSI Approved :: BSD License
Classifier: Topic :: Software Development :: Libraries :: Python Modules
Classifier: Programming Language :: Python
Classifier: Programming Language :: Python :: 2
Classifier: Programming Language :: Python :: 2.7
Classifier: Programming Language :: Python :: 3
Classifier: Programming Language :: Python :: 3.5
Classifier: Programming Language :: Python :: 3.6
Classifier: Programming Language :: Python :: 3.7
Classifier: Programming Language :: Python :: 3.8
Requires-Dist: valid8 (>=2.1)
Requires-Dist: requests
Requires-Dist: jinja2
Requires-Dist: decopatch
Requires-Dist: makefun
Requires-Dist: yamlable (>=0.7)
Requires-Dist: autoclass (>=1.15)
Requires-Dist: numpy
Requires-Dist: pandas
Requires-Dist: functools32 ; python_version < "3.3"
